Workbook

Sheet Présentation
A1: EcoFlow – Cahier des spécifications : Epics & User Stories
A3: Projet | B3: EcoFlow – application Flutter qui relie citoyens, collecteurs et entreprises de recyclage.
A4: Objectif | B4: Permettre à un citoyen de scanner ses déchets (IA), d'en estimer la valeur, de demander une collecte, puis d'alimenter une chaîne circulaire : collecteur → centre de tri → recycleur → entreprise.
A5: Espaces (4 interfaces) | B5: Citoyen · Collecteur · Recycleur / Entreprise · Administrateur
A6: Modules IA (4) | B6: 1) Vision IA (YOLOv8/YOLO11) 2) Estimation intelligente 3) Prédiction des volumes 4) Optimisation d'itinéraires
A7: Fonctions clés | B7: Recycle Wallet (EcoPoints, récompenses partenaires) · Marketplace circulaire B2B · Suivi temps réel · Supervision admin (tonnes, CO₂ évité)
A9: Feuilles du classeur | B9: Epics : liste des 14 epics avec compteurs automatiques · User Stories : backlog détaillé filtrable · Synthèse : répartitions par acteur, priorité, release et module IA
A11: LÉGENDE
A12: Priorité (MoSCoW) | B12: Must = indispensable · Should = important · Could = souhaitable
A13: Points | B13: Estimation de complexité (suite de Fibonacci : 1, 2, 3, 5, 8, 13) – à ajuster avec l'équipe.
A14: Release | B14: MVP = première version fonctionnelle · V1 = consolidation · V2 = extension (prédiction, marketplace, etc.)
A15: Statut | B15: À faire · En cours · En revue · Terminé (liste déroulante dans la feuille User Stories)
A16: Cellules à modifier | B16: Colonnes Priorité, Points, Release et Statut de la feuille User Stories. Les compteurs des feuilles Epics et Synthèse se recalculent automatiquement.
A17: Hypothèses | B17: Priorités, points et releases sont des propositions initiales, non validées par un Product Owner. Les critères d'acceptation sont concis et à détailler en sprint planning.

Sheet Epics
A1: ID Epic | B1: Epic | C1: Description | D1: Acteurs concernés | E1: Priorité | F1: Release cible | G1: Valeur métier | H1: Nb user stories | I1: Total points
A2: E01 | B2: Authentification & profils | C2: Inscription, connexion, gestion des rôles (citoyen, collecteur, recycleur, admin), vérification des professionnels et profils. | D2: Tous | E2: Must | F2: MVP | G2: Accéder à la plateforme de façon sécurisée avec le bon rôle. | H2: =COUNTIF('User Stories'!$B$2:$B$133,A2) -> 10 | I2: =SUMIF('User Stories'!$B$2:$B$133,A2,'User Stories'!$H$2:$H$133) -> 31
A3: E02 | B3: Vision IA – scan des déchets | C3: Détection et classification des déchets par photo avec YOLOv8/YOLO11 : comptage, type de matière, recyclabilité. | D3: Citoyen, Administrateur | E3: Must | F3: MVP | G3: Cœur différenciant : transformer une photo en données exploitables. | H3: =COUNTIF('User Stories'!$B$2:$B$133,A3) -> 12 | I3: =SUMIF('User Stories'!$B$2:$B$133,A3,'User Stories'!$H$2:$H$133) -> 48
A4: E03 | B4: Estimation intelligente quantité & valeur | C4: Estimation du poids et de la valeur en DT, indice de confiance, confirmation humaine et calibrage par la pesée réelle. | D4: Citoyen, Collecteur, Administrateur | E4: Must | F4: MVP | G4: Donner une valeur concrète et transparente avant la collecte. | H4: =COUNTIF('User Stories'!$B$2:$B$133,A4) -> 8 | I4: =SUMIF('User Stories'!$B$2:$B$133,A4,'User Stories'!$H$2:$H$133) -> 32
A5: E04 | B5: Demande de collecte | C5: Création, modification, annulation d'une demande avec lieu et plage horaire ; matching avec un collecteur proche. | D5: Citoyen, Système | E5: Must | F5: MVP | G5: Faire le lien entre citoyens et collecteurs. | H5: =COUNTIF('User Stories'!$B$2:$B$133,A5) -> 11 | I5: =SUMIF('User Stories'!$B$2:$B$133,A5,'User Stories'!$H$2:$H$133) -> 40
A6: E05 | B6: Espace collecteur & missions | C6: Disponibilité, missions, navigation, pesée, validation, historique, revenus et dépôt au centre de tri. | D6: Collecteur | E6: Must | F6: MVP | G6: Permettre aux collecteurs de travailler efficacement et d'être rémunérés. | H6: =COUNTIF('User Stories'!$B$2:$B$133,A6) -> 14 | I6: =SUMIF('User Stories'!$B$2:$B$133,A6,'User Stories'!$H$2:$H$133) -> 51
A7: E06 | B7: Optimisation IA des itinéraires | C7: Tournées multi-collectes optimisées (km, temps, carburant) sous contraintes de capacité et de créneaux. | D7: Collecteur, Administrateur, Système | E7: Should | F7: V1 | G7: Réduire coûts, temps et émissions. | H7: =COUNTIF('User Stories'!$B$2:$B$133,A7) -> 7 | I7: =SUMIF('User Stories'!$B$2:$B$133,A7,'User Stories'!$H$2:$H$133) -> 48
A8: E07 | B8: Suivi temps réel & notifications | C8: Suivi du collecteur sur carte, ETA, notifications push/SMS, messagerie/appel masqué. | D8: Citoyen, Collecteur | E8: Must | F8: MVP | G8: Transparence et confiance pendant la collecte. | H8: =COUNTIF('User Stories'!$B$2:$B$133,A8) -> 6 | I8: =SUMIF('User Stories'!$B$2:$B$133,A8,'User Stories'!$H$2:$H$133) -> 27
A9: E08 | B9: Recycle Wallet & EcoPoints | C9: Portefeuille de points, règles d'attribution, catalogue de récompenses partenaires, anti-fraude, gamification. | D9: Citoyen, Administrateur | E9: Must | F9: V1 | G9: Motiver les citoyens à recycler durablement. | H9: =COUNTIF('User Stories'!$B$2:$B$133,A9) -> 10 | I9: =SUMIF('User Stories'!$B$2:$B$133,A9,'User Stories'!$H$2:$H$133) -> 47
A10: E09 | B10: Espace recycleur – dashboard & stocks | C10: Réception des lots, traçabilité, stocks par matière (PET, HDPE, PP, autres), rapports et export. | D10: Recycleur / Entreprise | E10: Must | F10: V1 | G10: Piloter les volumes reçus et les stocks. | H10: =COUNTIF('User Stories'!$B$2:$B$133,A10) -> 9 | I10: =SUMIF('User Stories'!$B$2:$B$133,A10,'User Stories'!$H$2:$H$133) -> 39
A11: E10 | B11: Prédiction IA des volumes | C11: Prévision des volumes de plastique par zone, cartes de chaleur, alertes et suivi de précision du modèle. | D11: Recycleur, Administrateur | E11: Should | F11: V2 | G11: Anticiper l'approvisionnement et planifier les ressources. | H11: =COUNTIF('User Stories'!$B$2:$B$133,A11) -> 6 | I11: =SUMIF('User Stories'!$B$2:$B$133,A11,'User Stories'!$H$2:$H$133) -> 42
A12: E11 | B12: Marketplace circulaire B2B | C12: Demandes d'achat et offres de vente de matières recyclées, recherche, négociation, commandes et notation. | D12: Recycleur / Entreprise, Administrateur | E12: Should | F12: V2 | G12: Boucler l'économie circulaire jusqu'à l'entreprise. | H12: =COUNTIF('User Stories'!$B$2:$B$133,A12) -> 12 | I12: =SUMIF('User Stories'!$B$2:$B$133,A12,'User Stories'!$H$2:$H$133) -> 64
A13: E12 | B13: Administration & supervision | C13: Gestion des utilisateurs, validations, carte des collectes, statistiques, CO₂ évité, litiges et journal d'audit. | D13: Administrateur | E13: Must | F13: MVP | G13: Superviser et piloter toute la plateforme. | H13: =COUNTIF('User Stories'!$B$2:$B$133,A13) -> 12 | I13: =SUMIF('User Stories'!$B$2:$B$133,A13,'User Stories'!$H$2:$H$133) -> 65
... A15: E14 | B15: Exigences transverses & qualité | C15: Sécurité, performance, disponibilité, hors-ligne, conformité données, accessibilité, CI/CD, monitoring. | D15: Système | E15: Must | F15: MVP | G15: Garantir robustesse, sécurité et conformité. | H15: =COUNTIF('User Stories'!$B$2:$B$133,A15) -> 10 | I15: =SUMIF('User Stories'!$B$2:$B$133,A15,'User Stories'!$H$2:$H$133) -> 52
A16: TOTAL | H16: =SUM(H2:H15) -> 132 | I16: =SUM(I2:I15) -> 608

Sheet User Stories
A1: ID | B1: ID Epic | C1: Epic | D1: Acteur | E1: User story | F1: Critères d'acceptation | G1: Priorité | H1: Points | I1: Release | J1: Module IA | K1: Statut
A2: US-001 | B2: E01 | C2: =INDEX(Epics!$B$2:$B$15,MATCH(B2,Epics!$A$2:$A$15,0)) -> Authentification & profils | D2: Utilisateur | E2: En tant qu'utilisateur, je veux m'inscrire avec mon numéro de téléphone (code OTP par SMS) ou mon e-mail afin de créer un compte rapidement. | F2: Le code OTP est valide 5 min ; compte créé après vérification ; erreurs claires si numéro invalide. | G2: Must | H2: 3 | I2: MVP | J2: — | K2: À faire
A3: US-002 | B3: E01 | C3: =INDEX(Epics!$B$2:$B$15,MATCH(B3,Epics!$A$2:$A$15,0)) -> Authentification & profils | D3: Utilisateur | E3: En tant qu'utilisateur, je veux me connecter avec e-mail/mot de passe ou compte Google afin de accéder à mon espace sans friction. | F3: Session persistante via JWT + refresh token ; déconnexion possible ; verrouillage après 5 échecs. | G3: Must | H3: 3 | I3: MVP | J3: — | K3: À faire
A4: US-003 | B4: E01 | C4: =INDEX(Epics!$B$2:$B$15,MATCH(B4,Epics!$A$2:$A$15,0)) -> Authentification & profils | D4: Utilisateur | E4: En tant qu'utilisateur, je veux choisir mon rôle (citoyen, collecteur, recycleur) à l'inscription afin de accéder à l'interface adaptée. | F4: Le rôle détermine la navigation Flutter ; un rôle admin ne peut pas être choisi. | G4: Must | H4: 2 | I4: MVP | J4: — | K4: À faire
A5: US-004 | B5: E01 | C5: =INDEX(Epics!$B$2:$B$15,MATCH(B5,Epics!$A$2:$A$15,0)) -> Authentification & profils | D5: Utilisateur | E5: En tant qu'utilisateur, je veux réinitialiser mon mot de passe afin de récupérer l'accès à mon compte. | F5: Lien/code envoyé ; expire après 15 min ; ancien mot de passe invalidé. | G5: Must | H5: 2 | I5: MVP | J5: — | K5: À faire
A6: US-005 | B6: E01 | C6: =INDEX(Epics!$B$2:$B$15,MATCH(B6,Epics!$A$2:$A$15,0)) -> Authentification & profils | D6: Citoyen | E6: En tant que citoyen, je veux gérer mon profil et mes adresses enregistrées afin de pré-remplir mes demandes de collecte. | F6: Ajout/modification/suppression d'adresses avec position GPS ; adresse par défaut. | G6: Should | H6: 3 | I6: MVP | J6: — | K6: À faire
A7: US-006 | B7: E01 | C7: =INDEX(Epics!$B$2:$B$15,MATCH(B7,Epics!$A$2:$A$15,0)) -> Authentification & profils | D7: Collecteur | E7: En tant que collecteur, je veux soumettre mes documents (CIN, permis, carte grise, photo véhicule) afin de être vérifié et autorisé à collecter. | F7: Upload de fichiers ; statut « en attente / validé / refusé » visible ; motif de refus affiché. | G7: Must | H7: 5 | I7: MVP | J7: — | K7: À faire
A8: US-007 | B8: E01 | C8: =INDEX(Epics!$B$2:$B$15,MATCH(B8,Epics!$A$2:$A$15,0)) -> Authentification & profils | D8: Recycleur / Entreprise | E8: En tant que recycleur / entreprise, je veux créer le profil de mon entreprise (raison sociale, matricule fiscal, matières traitées, capacités) afin de être référencé comme recycleur fiable. | F8: Champs obligatoires validés ; profil soumis à validation admin. | G8: Must | H8: 3 | I8: V1 | J8: — | K8: À faire
A9: US-008 | B9: E01 | C9: =INDEX(Epics!$B$2:$B$15,MATCH(B9,Epics!$A$2:$A$15,0)) -> Authentification & profils | D9: Utilisateur | E9: En tant qu'utilisateur, je veux choisir la langue de l'application (français, arabe, anglais) afin de utiliser l'application dans ma langue. | F9: Changement à chaud ; support RTL pour l'arabe. | G9: Should | H9: 5 | I9: V1 | J9: — | K9: À faire
A10: US-009 | B10: E01 | C10: =INDEX(Epics!$B$2:$B$15,MATCH(B10,Epics!$A$2:$A$15,0)) -> Authentification & profils | D10: Utilisateur | E10: En tant qu'utilisateur, je veux gérer mes préférences de notifications afin de ne recevoir que les alertes utiles. | F10: Activation/désactivation par catégorie (statut collecte, points, marketplace). | G10: Could | H10: 2 | I10: V1 | J10: — | K10: À faire
A11: US-010 | B11: E01 | C11: =INDEX(Epics!$B$2:$B$15,MATCH(B11,Epics!$A$2:$A$15,0)) -> Authentification & profils | D11: Utilisateur | E11: En tant qu'utilisateur, je veux supprimer mon compte et mes données personnelles afin de garder le contrôle de mes données. | F11: Confirmation en 2 étapes ; données anonymisées sous 30 jours ; historique financier conservé légalement. | G11: Should | H11: 3 | I11: V1 | J11: — | K11: À faire
A12: US-011 | B12: E02 | C12: =INDEX(Epics!$B$2:$B$15,MATCH(B12,Epics!$A$2:$A$15,0)) -> Vision IA – scan des déchets | D12: Citoyen | E12: En tant que citoyen, je veux prendre en photo mes déchets avec la caméra de l'application afin de lancer une analyse automatique. | F12: Permission caméra demandée ; aperçu avant envoi ; résultat en moins de 5 s en 4G. | G12: Must | H12: 3 | I12: MVP | J12: Vision IA | K12: À faire
A13: US-012 | B13: E02 | C13: =INDEX(Epics!$B$2:$B$15,MATCH(B13,Epics!$A$2:$A$15,0)) -> Vision IA – scan des déchets | D13: Citoyen | E13: En tant que citoyen, je veux importer une ou plusieurs photos depuis ma galerie afin de analyser des photos déjà prises. | F13: Sélection multiple (max 5) ; formats JPG/PNG ; compression avant envoi. | G13: Should | H13: 2 | I13: MVP | J13: Vision IA | K13: À faire
... A133: US-132 | B133: E14 | C133: =INDEX(Epics!$B$2:$B$15,MATCH(B133,Epics!$A$2:$A$15,0)) -> Exigences transverses & qualité | D133: Système | E133: En tant que système, je dois sauvegarder automatiquement les bases de données et fichiers afin de éviter toute perte de données. | F133: Sauvegardes quotidiennes ; restauration testée. | G133: Must | H133: 3 | I133: MVP | J133: — | K133: À faire

Sheet Synthèse
A1: Synthèse du backlog
A3: Par acteur
A4: Acteur | B4: Nb stories | C4: Points | D4: % des stories
A5: Citoyen | B5: =COUNTIF('User Stories'!$D$2:$D$133,A5) -> 38 | C5: =SUMIF('User Stories'!$D$2:$D$133,A5,'User Stories'!$H$2:$H$133) -> 144 | D5: =IF($B$11=0,0,B5/$B$11) -> 0.28787879
A6: Collecteur | B6: =COUNTIF('User Stories'!$D$2:$D$133,A6) -> 20 | C6: =SUMIF('User Stories'!$D$2:$D$133,A6,'User Stories'!$H$2:$H$133) -> 86 | D6: =IF($B$11=0,0,B6/$B$11) -> 0.15151515
A7: Recycleur / Entreprise | B7: =COUNTIF('User Stories'!$D$2:$D$133,A7) -> 22 | C7: =SUMIF('User Stories'!$D$2:$D$133,A7,'User Stories'!$H$2:$H$133) -> 113 | D7: =IF($B$11=0,0,B7/$B$11) -> 0.16666667
A8: Administrateur | B8: =COUNTIF('User Stories'!$D$2:$D$133,A8) -> 23 | C8: =SUMIF('User Stories'!$D$2:$D$133,A8,'User Stories'!$H$2:$H$133) -> 113 | D8: =IF($B$11=0,0,B8/$B$11) -> 0.17424242
A9: Utilisateur | B9: =COUNTIF('User Stories'!$D$2:$D$133,A9) -> 10 | C9: =SUMIF('User Stories'!$D$2:$D$133,A9,'User Stories'!$H$2:$H$133) -> 36 | D9: =IF($B$11=0,0,B9/$B$11) -> 0.075757576
A10: Système | B10: =COUNTIF('User Stories'!$D$2:$D$133,A10) -> 19 | C10: =SUMIF('User Stories'!$D$2:$D$133,A10,'User Stories'!$H$2:$H$133) -> 116 | D10: =IF($B$11=0,0,B10/$B$11) -> 0.14393939
A11: TOTAL | B11: =SUM(B5:B10) -> 132 | C11: =SUM(C5:C10) -> 608 | D11: =IF($B$11=0,0,B11/$B$11) -> 1
A13: Par priorité (MoSCoW)
A14: Priorité | B14: Nb stories | C14: Points | D14: % des stories
A15: Must | B15: =COUNTIF('User Stories'!$G$2:$G$133,A15) -> 50 | C15: =SUMIF('User Stories'!$G$2:$G$133,A15,'User Stories'!$H$2:$H$133) -> 216 | D15: =IF($B$18=0,0,B15/$B$18) -> 0.37878788
A16: Should | B16: =COUNTIF('User Stories'!$G$2:$G$133,A16) -> 52 | C16: =SUMIF('User Stories'!$G$2:$G$133,A16,'User Stories'!$H$2:$H$133) -> 239 | D16: =IF($B$18=0,0,B16/$B$18) -> 0.39393939
A17: Could | B17: =COUNTIF('User Stories'!$G$2:$G$133,A17) -> 30 | C17: =SUMIF('User Stories'!$G$2:$G$133,A17,'User Stories'!$H$2:$H$133) -> 153 | D17: =IF($B$18=0,0,B17/$B$18) -> 0.22727273
A18: TOTAL | B18: =SUM(B15:B17) -> 132 | C18: =SUM(C15:C17) -> 608 | D18: =IF($B$18=0,0,B18/$B$18) -> 1
A20: Par release
A21: Release | B21: Nb stories | C21: Points | D21: % des stories
A22: MVP | B22: =COUNTIF('User Stories'!$I$2:$I$133,A22) -> 49 | C22: =SUMIF('User Stories'!$I$2:$I$133,A22,'User Stories'!$H$2:$H$133) -> 194 | D22: =IF($B$25=0,0,B22/$B$25) -> 0.37121212
A23: V1 | B23: =COUNTIF('User Stories'!$I$2:$I$133,A23) -> 42 | C23: =SUMIF('User Stories'!$I$2:$I$133,A23,'User Stories'!$H$2:$H$133) -> 194 | D23: =IF($B$25=0,0,B23/$B$25) -> 0.31818182
A24: V2 | B24: =COUNTIF('User Stories'!$I$2:$I$133,A24) -> 41 | C24: =SUMIF('User Stories'!$I$2:$I$133,A24,'User Stories'!$H$2:$H$133) -> 220 | D24: =IF($B$25=0,0,B24/$B$25) -> 0.31060606
A25: TOTAL | B25: =SUM(B22:B24) -> 132 | C25: =SUM(C22:C24) -> 608 | D25: =IF($B$25=0,0,B25/$B$25) -> 1
A27: Par module IA
A28: Module IA | B28: Nb stories | C28: Points | D28: % des stories
A29: Vision IA | B29: =COUNTIF('User Stories'!$J$2:$J$133,A29) -> 12 | C29: =SUMIF('User Stories'!$J$2:$J$133,A29,'User Stories'!$H$2:$H$133) -> 48 | D29: =IF($B$34=0,0,B29/$B$34) -> 0.090909091
A30: Estimation | B30: =COUNTIF('User Stories'!$J$2:$J$133,A30) -> 8 | C30: =SUMIF('User Stories'!$J$2:$J$133,A30,'User Stories'!$H$2:$H$133) -> 32 | D30: =IF($B$34=0,0,B30/$B$34) -> 0.060606061
A31: Prédiction | B31: =COUNTIF('User Stories'!$J$2:$J$133,A31) -> 7 | C31: =SUMIF('User Stories'!$J$2:$J$133,A31,'User Stories'!$H$2:$H$133) -> 50 | D31: =IF($B$34=0,0,B31/$B$34) -> 0.053030303
A32: Optimisation | B32: =COUNTIF('User Stories'!$J$2:$J$133,A32) -> 8 | C32: =SUMIF('User Stories'!$J$2:$J$133,A32,'User Stories'!$H$2:$H$133) -> 56 | D32: =IF($B$34=0,0,B32/$B$34) -> 0.060606061
A33: — | B33: =COUNTIF('User Stories'!$J$2:$J$133,A33) -> 97 | C33: =SUMIF('User Stories'!$J$2:$J$133,A33,'User Stories'!$H$2:$H$133) -> 422 | D33: =IF($B$34=0,0,B33/$B$34) -> 0.73484848
A34: TOTAL | B34: =SUM(B29:B33) -> 132 | C34: =SUM(C29:C33) -> 608 | D34: =IF($B$34=0,0,B34/$B$34) -> 1
A36: Par statut
A37: Statut | B37: Nb stories | C37: Points | D37: % des stories
A38: À faire | B38: =COUNTIF('User Stories'!$K$2:$K$133,A38) -> 132 | C38: =SUMIF('User Stories'!$K$2:$K$133,A38,'User Stories'!$H$2:$H$133) -> 608 | D38: =IF($B$42=0,0,B38/$B$42) -> 1
A39: En cours | B39: =COUNTIF('User Stories'!$K$2:$K$133,A39) -> 0 | C39: =SUMIF('User Stories'!$K$2:$K$133,A39,'User Stories'!$H$2:$H$133) -> 0 | D39: =IF($B$42=0,0,B39/$B$42) -> 0
A40: En revue | B40: =COUNTIF('User Stories'!$K$2:$K$133,A40) -> 0 | C40: =SUMIF('User Stories'!$K$2:$K$133,A40,'User Stories'!$H$2:$H$133) -> 0 | D40: =IF($B$42=0,0,B40/$B$42) -> 0
A41: Terminé | B41: =COUNTIF('User Stories'!$K$2:$K$133,A41) -> 0 | C41: =SUMIF('User Stories'!$K$2:$K$133,A41,'User Stories'!$H$2:$H$133) -> 0 | D41: =IF($B$42=0,0,B41/$B$42) -> 0
A42: TOTAL | B42: =SUM(B38:B41) -> 132 | C42: =SUM(C38:C41) -> 608 | D42: =IF($B$42=0,0,B42/$B$42) -> 1
